apt_repoman/__init__.py
apt_repoman/cli.py
apt_repoman/config.py
apt_repoman/connection.py
apt_repoman/repo.py
apt_repoman/repodb.py
apt_repoman/utils.py
apt_repoman/resources/__init__.py
apt_repoman/resources/logconfig.json
apt_repoman-1.0.7.dist-info/LICENSE.txt
apt_repoman-1.0.7.dist-info/METADATA
apt_repoman-1.0.7.dist-info/WHEEL
apt_repoman-1.0.7.dist-info/entry_points.txt
apt_repoman-1.0.7.dist-info/top_level.txt
apt_repoman-1.0.7.dist-info/RECORD
