Metadata-Version: 2.1
Name: apt-repoman
Version: 1.0.7
Summary: A high performance Debian APT repository based on Amazon Web Services
Home-page: https://github.com/memory/repoman
Author: Nathan J. Mehl
Author-email: pypi@memory.blank.org
License: UNKNOWN
Download-URL: https://github.com/memory/repoman/tarball/1.0.7
Keywords: apt,debian,dpkg,packaging
Platform: UNKNOWN
Classifier: Development Status :: 5 - Production/Stable
Classifier: License :: OSI Approved :: Apache Software License
Classifier: Programming Language :: Python :: 2.7
Classifier: Programming Language :: Python :: 3.4
Classifier: Programming Language :: Python :: 3.5
Classifier: Programming Language :: Python :: 3.6
Classifier: Programming Language :: Python :: 3.7
Classifier: Programming Language :: Python :: 3.8
Classifier: Programming Language :: Python :: Implementation :: CPython
Classifier: Topic :: System :: Archiving :: Packaging
Requires-Dist: PGPy (==0.5.2)
Requires-Dist: ansicolors (==1.1.8)
Requires-Dist: boto3 (==1.4.4)
Requires-Dist: configargparse (==0.12.0)
Requires-Dist: pydpkg (==1.3.3)
Requires-Dist: pysectools (==0.4.2)
Requires-Dist: tabulate (==0.7.7)
Provides-Extra: test
Requires-Dist: mock (==2.0.0) ; extra == 'test'
Requires-Dist: pep8 (==1.7.0) ; extra == 'test'
Requires-Dist: pylint (==1.7.1) ; extra == 'test'
Requires-Dist: pytest (==3.1.1) ; extra == 'test'
